<?xml version="1.0" encoding="utf-8"?>
<StaticLibrary>
  <RelativeName>um\x64\resutils.lib</RelativeName>
  <OriginalPath>C:\Program Files (x86)\Windows Kits\10\Lib\10.0.17134.0\um\x64\resutils.lib</OriginalPath>
  <ReferencedLibraries>
    <DynamicLibrary Name="RESUTILS.dll" />
  </ReferencedLibraries>
  <ExportedSymbols>
    <Symbol Name="*))" />
    <Symbol Name="CloseClusterCryptProvider">
      <Definitions>
        <DynamicLibrary Name="RESUTILS.dll" />
      </Definitions>
    </Symbol>
    <Symbol Name="ClusAddClusterHealthFault">
      <Definitions>
        <DynamicLibrary Name="RESUTILS.dll" />
      </Definitions>
    </Symbol>
    <Symbol Name="ClusGetClusterHealthFaults">
      <Definitions>
        <DynamicLibrary Name="RESUTILS.dll" />
      </Definitions>
    </Symbol>
    <Symbol Name="ClusRemoveClusterHealthFault">
      <Definitions>
        <DynamicLibrary Name="RESUTILS.dll" />
      </Definitions>
    </Symbol>
    <Symbol Name="ClusWorkerCheckTerminate">
      <Definitions>
        <DynamicLibrary Name="RESUTILS.dll" />
      </Definitions>
    </Symbol>
    <Symbol Name="ClusWorkerCreate">
      <Definitions>
        <DynamicLibrary Name="RESUTILS.dll" />
      </Definitions>
    </Symbol>
    <Symbol Name="ClusWorkerTerminate">
      <Definitions>
        <DynamicLibrary Name="RESUTILS.dll" />
      </Definitions>
    </Symbol>
    <Symbol Name="ClusWorkerTerminateEx">
      <Definitions>
        <DynamicLibrary Name="RESUTILS.dll" />
      </Definitions>
    </Symbol>
    <Symbol Name="ClusWorkersTerminate">
      <Definitions>
        <DynamicLibrary Name="RESUTILS.dll" />
      </Definitions>
    </Symbol>
    <Symbol Name="ClusterClearBackupStateForSharedVolume">
      <Definitions>
        <DynamicLibrary Name="RESUTILS.dll" />
      </Definitions>
    </Symbol>
    <Symbol Name="ClusterDecrypt">
      <Definitions>
        <DynamicLibrary Name="RESUTILS.dll" />
      </Definitions>
    </Symbol>
    <Symbol Name="ClusterEncrypt">
      <Definitions>
        <DynamicLibrary Name="RESUTILS.dll" />
      </Definitions>
    </Symbol>
    <Symbol Name="ClusterGetVolumeNameForVolumeMountPoint">
      <Definitions>
        <DynamicLibrary Name="RESUTILS.dll" />
      </Definitions>
    </Symbol>
    <Symbol Name="ClusterGetVolumePathName">
      <Definitions>
        <DynamicLibrary Name="RESUTILS.dll" />
      </Definitions>
    </Symbol>
    <Symbol Name="ClusterIsPathOnSharedVolume">
      <Definitions>
        <DynamicLibrary Name="RESUTILS.dll" />
      </Definitions>
    </Symbol>
    <Symbol Name="ClusterPrepareSharedVolumeForBackup">
      <Definitions>
        <DynamicLibrary Name="RESUTILS.dll" />
      </Definitions>
    </Symbol>
    <Symbol Name="ClusterSharedVolumeCheckSnapshotPresence">
      <Definitions>
        <DynamicLibrary Name="RESUTILS.dll" />
      </Definitions>
    </Symbol>
    <Symbol Name="ClusterSharedVolumeCreateSnapshot">
      <Definitions>
        <DynamicLibrary Name="RESUTILS.dll" />
      </Definitions>
    </Symbol>
    <Symbol Name="ClusterSharedVolumeReleaseSnapshot">
      <Definitions>
        <DynamicLibrary Name="RESUTILS.dll" />
      </Definitions>
    </Symbol>
    <Symbol Name="CreateClusterStorageSpacesClustering">
      <Definitions>
        <DynamicLibrary Name="RESUTILS.dll" />
      </Definitions>
    </Symbol>
    <Symbol Name="CreateClusterStorageSpacesResourceLocator">
      <Definitions>
        <DynamicLibrary Name="RESUTILS.dll" />
      </Definitions>
    </Symbol>
    <Symbol Name="CreateClusterStorageSpacesSubProvider">
      <Definitions>
        <DynamicLibrary Name="RESUTILS.dll" />
      </Definitions>
    </Symbol>
    <Symbol Name="FreeClusterCrypt">
      <Definitions>
        <DynamicLibrary Name="RESUTILS.dll" />
      </Definitions>
    </Symbol>
    <Symbol Name="FreeClusterHealthFault">
      <Definitions>
        <DynamicLibrary Name="RESUTILS.dll" />
      </Definitions>
    </Symbol>
    <Symbol Name="FreeClusterHealthFaultArray">
      <Definitions>
        <DynamicLibrary Name="RESUTILS.dll" />
      </Definitions>
    </Symbol>
    <Symbol Name="InitializeClusterHealthFault">
      <Definitions>
        <DynamicLibrary Name="RESUTILS.dll" />
      </Definitions>
    </Symbol>
    <Symbol Name="InitializeClusterHealthFaultArray">
      <Definitions>
        <DynamicLibrary Name="RESUTILS.dll" />
      </Definitions>
    </Symbol>
    <Symbol Name="OpenClusterCryptProvider">
      <Definitions>
        <DynamicLibrary Name="RESUTILS.dll" />
      </Definitions>
    </Symbol>
    <Symbol Name="ResUtilAddUnknownProperties">
      <Definitions>
        <DynamicLibrary Name="RESUTILS.dll" />
      </Definitions>
    </Symbol>
    <Symbol Name="ResUtilCreateDirectoryTree">
      <Definitions>
        <DynamicLibrary Name="RESUTILS.dll" />
      </Definitions>
    </Symbol>
    <Symbol Name="ResUtilDupGroup">
      <Definitions>
        <DynamicLibrary Name="RESUTILS.dll" />
      </Definitions>
    </Symbol>
    <Symbol Name="ResUtilDupParameterBlock">
      <Definitions>
        <DynamicLibrary Name="RESUTILS.dll" />
      </Definitions>
    </Symbol>
    <Symbol Name="ResUtilDupResource">
      <Definitions>
        <DynamicLibrary Name="RESUTILS.dll" />
      </Definitions>
    </Symbol>
    <Symbol Name="ResUtilDupString">
      <Definitions>
        <DynamicLibrary Name="RESUTILS.dll" />
      </Definitions>
    </Symbol>
    <Symbol Name="ResUtilEnumGroups">
      <Definitions>
        <DynamicLibrary Name="RESUTILS.dll" />
      </Definitions>
    </Symbol>
    <Symbol Name="ResUtilEnumGroupsEx">
      <Definitions>
        <DynamicLibrary Name="RESUTILS.dll" />
      </Definitions>
    </Symbol>
    <Symbol Name="ResUtilEnumPrivateProperties">
      <Definitions>
        <DynamicLibrary Name="RESUTILS.dll" />
      </Definitions>
    </Symbol>
    <Symbol Name="ResUtilEnumProperties">
      <Definitions>
        <DynamicLibrary Name="RESUTILS.dll" />
      </Definitions>
    </Symbol>
    <Symbol Name="ResUtilEnumResources">
      <Definitions>
        <DynamicLibrary Name="RESUTILS.dll" />
      </Definitions>
    </Symbol>
    <Symbol Name="ResUtilEnumResourcesEx">
      <Definitions>
        <DynamicLibrary Name="RESUTILS.dll" />
      </Definitions>
    </Symbol>
    <Symbol Name="ResUtilEnumResourcesEx2">
      <Definitions>
        <DynamicLibrary Name="RESUTILS.dll" />
      </Definitions>
    </Symbol>
    <Symbol Name="ResUtilExpandEnvironmentStrings">
      <Definitions>
        <DynamicLibrary Name="RESUTILS.dll" />
      </Definitions>
    </Symbol>
    <Symbol Name="ResUtilFindBinaryProperty">
      <Definitions>
        <DynamicLibrary Name="RESUTILS.dll" />
      </Definitions>
    </Symbol>
    <Symbol Name="ResUtilFindDependentDiskResourceDriveLetter">
      <Definitions>
        <DynamicLibrary Name="RESUTILS.dll" />
      </Definitions>
    </Symbol>
    <Symbol Name="ResUtilFindDwordProperty">
      <Definitions>
        <DynamicLibrary Name="RESUTILS.dll" />
      </Definitions>
    </Symbol>
    <Symbol Name="ResUtilFindExpandSzProperty">
      <Definitions>
        <DynamicLibrary Name="RESUTILS.dll" />
      </Definitions>
    </Symbol>
    <Symbol Name="ResUtilFindExpandedSzProperty">
      <Definitions>
        <DynamicLibrary Name="RESUTILS.dll" />
      </Definitions>
    </Symbol>
    <Symbol Name="ResUtilFindFileTimeProperty">
      <Definitions>
        <DynamicLibrary Name="RESUTILS.dll" />
      </Definitions>
    </Symbol>
    <Symbol Name="ResUtilFindLongProperty">
      <Definitions>
        <DynamicLibrary Name="RESUTILS.dll" />
      </Definitions>
    </Symbol>
    <Symbol Name="ResUtilFindMultiSzProperty">
      <Definitions>
        <DynamicLibrary Name="RESUTILS.dll" />
      </Definitions>
    </Symbol>
    <Symbol Name="ResUtilFindSzProperty">
      <Definitions>
        <DynamicLibrary Name="RESUTILS.dll" />
      </Definitions>
    </Symbol>
    <Symbol Name="ResUtilFindULargeIntegerProperty">
      <Definitions>
        <DynamicLibrary Name="RESUTILS.dll" />
      </Definitions>
    </Symbol>
    <Symbol Name="ResUtilFreeEnvironment">
      <Definitions>
        <DynamicLibrary Name="RESUTILS.dll" />
      </Definitions>
    </Symbol>
    <Symbol Name="ResUtilFreeParameterBlock">
      <Definitions>
        <DynamicLibrary Name="RESUTILS.dll" />
      </Definitions>
    </Symbol>
    <Symbol Name="ResUtilGetAllProperties">
      <Definitions>
        <DynamicLibrary Name="RESUTILS.dll" />
      </Definitions>
    </Symbol>
    <Symbol Name="ResUtilGetBinaryProperty">
      <Definitions>
        <DynamicLibrary Name="RESUTILS.dll" />
      </Definitions>
    </Symbol>
    <Symbol Name="ResUtilGetBinaryValue">
      <Definitions>
        <DynamicLibrary Name="RESUTILS.dll" />
      </Definitions>
    </Symbol>
    <Symbol Name="ResUtilGetClusterGroupType">
      <Definitions>
        <DynamicLibrary Name="RESUTILS.dll" />
      </Definitions>
    </Symbol>
    <Symbol Name="ResUtilGetClusterId">
      <Definitions>
        <DynamicLibrary Name="RESUTILS.dll" />
      </Definitions>
    </Symbol>
    <Symbol Name="ResUtilGetClusterRoleState">
      <Definitions>
        <DynamicLibrary Name="RESUTILS.dll" />
      </Definitions>
    </Symbol>
    <Symbol Name="ResUtilGetCoreClusterResources">
      <Definitions>
        <DynamicLibrary Name="RESUTILS.dll" />
      </Definitions>
    </Symbol>
    <Symbol Name="ResUtilGetCoreClusterResourcesEx">
      <Definitions>
        <DynamicLibrary Name="RESUTILS.dll" />
      </Definitions>
    </Symbol>
    <Symbol Name="ResUtilGetCoreGroup">
      <Definitions>
        <DynamicLibrary Name="RESUTILS.dll" />
      </Definitions>
    </Symbol>
    <Symbol Name="ResUtilGetDwordProperty">
      <Definitions>
        <DynamicLibrary Name="RESUTILS.dll" />
      </Definitions>
    </Symbol>
    <Symbol Name="ResUtilGetDwordValue">
      <Definitions>
        <DynamicLibrary Name="RESUTILS.dll" />
      </Definitions>
    </Symbol>
    <Symbol Name="ResUtilGetEnvironmentWithNetName">
      <Definitions>
        <DynamicLibrary Name="RESUTILS.dll" />
      </Definitions>
    </Symbol>
    <Symbol Name="ResUtilGetFileTimeProperty">
      <Definitions>
        <DynamicLibrary Name="RESUTILS.dll" />
      </Definitions>
    </Symbol>
    <Symbol Name="ResUtilGetLongProperty">
      <Definitions>
        <DynamicLibrary Name="RESUTILS.dll" />
      </Definitions>
    </Symbol>
    <Symbol Name="ResUtilGetMultiSzProperty">
      <Definitions>
        <DynamicLibrary Name="RESUTILS.dll" />
      </Definitions>
    </Symbol>
    <Symbol Name="ResUtilGetPrivateProperties">
      <Definitions>
        <DynamicLibrary Name="RESUTILS.dll" />
      </Definitions>
    </Symbol>
    <Symbol Name="ResUtilGetProperties">
      <Definitions>
        <DynamicLibrary Name="RESUTILS.dll" />
      </Definitions>
    </Symbol>
    <Symbol Name="ResUtilGetPropertiesToParameterBlock">
      <Definitions>
        <DynamicLibrary Name="RESUTILS.dll" />
      </Definitions>
    </Symbol>
    <Symbol Name="ResUtilGetProperty">
      <Definitions>
        <DynamicLibrary Name="RESUTILS.dll" />
      </Definitions>
    </Symbol>
    <Symbol Name="ResUtilGetPropertyFormats">
      <Definitions>
        <DynamicLibrary Name="RESUTILS.dll" />
      </Definitions>
    </Symbol>
    <Symbol Name="ResUtilGetPropertySize">
      <Definitions>
        <DynamicLibrary Name="RESUTILS.dll" />
      </Definitions>
    </Symbol>
    <Symbol Name="ResUtilGetQwordValue">
      <Definitions>
        <DynamicLibrary Name="RESUTILS.dll" />
      </Definitions>
    </Symbol>
    <Symbol Name="ResUtilGetResourceDependency">
      <Definitions>
        <DynamicLibrary Name="RESUTILS.dll" />
      </Definitions>
    </Symbol>
    <Symbol Name="ResUtilGetResourceDependencyByClass">
      <Definitions>
        <DynamicLibrary Name="RESUTILS.dll" />
      </Definitions>
    </Symbol>
    <Symbol Name="ResUtilGetResourceDependencyByClassEx">
      <Definitions>
        <DynamicLibrary Name="RESUTILS.dll" />
      </Definitions>
    </Symbol>
    <Symbol Name="ResUtilGetResourceDependencyByName">
      <Definitions>
        <DynamicLibrary Name="RESUTILS.dll" />
      </Definitions>
    </Symbol>
    <Symbol Name="ResUtilGetResourceDependencyByNameAndClass">
      <Definitions>
        <DynamicLibrary Name="RESUTILS.dll" />
      </Definitions>
    </Symbol>
    <Symbol Name="ResUtilGetResourceDependencyByNameEx">
      <Definitions>
        <DynamicLibrary Name="RESUTILS.dll" />
      </Definitions>
    </Symbol>
    <Symbol Name="ResUtilGetResourceDependencyEx">
      <Definitions>
        <DynamicLibrary Name="RESUTILS.dll" />
      </Definitions>
    </Symbol>
    <Symbol Name="ResUtilGetResourceDependentIPAddressProps">
      <Definitions>
        <DynamicLibrary Name="RESUTILS.dll" />
      </Definitions>
    </Symbol>
    <Symbol Name="ResUtilGetResourceName">
      <Definitions>
        <DynamicLibrary Name="RESUTILS.dll" />
      </Definitions>
    </Symbol>
    <Symbol Name="ResUtilGetResourceNameDependency">
      <Definitions>
        <DynamicLibrary Name="RESUTILS.dll" />
      </Definitions>
    </Symbol>
    <Symbol Name="ResUtilGetResourceNameDependencyEx">
      <Definitions>
        <DynamicLibrary Name="RESUTILS.dll" />
      </Definitions>
    </Symbol>
    <Symbol Name="ResUtilGetSzProperty">
      <Definitions>
        <DynamicLibrary Name="RESUTILS.dll" />
      </Definitions>
    </Symbol>
    <Symbol Name="ResUtilGetSzValue">
      <Definitions>
        <DynamicLibrary Name="RESUTILS.dll" />
      </Definitions>
    </Symbol>
    <Symbol Name="ResUtilGroupsEqual">
      <Definitions>
        <DynamicLibrary Name="RESUTILS.dll" />
      </Definitions>
    </Symbol>
    <Symbol Name="ResUtilIsPathValid">
      <Definitions>
        <DynamicLibrary Name="RESUTILS.dll" />
      </Definitions>
    </Symbol>
    <Symbol Name="ResUtilIsResourceClassEqual">
      <Definitions>
        <DynamicLibrary Name="RESUTILS.dll" />
      </Definitions>
    </Symbol>
    <Symbol Name="ResUtilLeftPaxosIsLessThanRight">
      <Definitions>
        <DynamicLibrary Name="RESUTILS.dll" />
      </Definitions>
    </Symbol>
    <Symbol Name="ResUtilNodeEnum">
      <Definitions>
        <DynamicLibrary Name="RESUTILS.dll" />
      </Definitions>
    </Symbol>
    <Symbol Name="ResUtilPaxosComparer">
      <Definitions>
        <DynamicLibrary Name="RESUTILS.dll" />
      </Definitions>
    </Symbol>
    <Symbol Name="ResUtilPropertyListFromParameterBlock">
      <Definitions>
        <DynamicLibrary Name="RESUTILS.dll" />
      </Definitions>
    </Symbol>
    <Symbol Name="ResUtilRemoveResourceServiceEnvironment">
      <Definitions>
        <DynamicLibrary Name="RESUTILS.dll" />
      </Definitions>
    </Symbol>
    <Symbol Name="ResUtilResourceDepEnum">
      <Definitions>
        <DynamicLibrary Name="RESUTILS.dll" />
      </Definitions>
    </Symbol>
    <Symbol Name="ResUtilResourceTypesEqual">
      <Definitions>
        <DynamicLibrary Name="RESUTILS.dll" />
      </Definitions>
    </Symbol>
    <Symbol Name="ResUtilResourcesEqual">
      <Definitions>
        <DynamicLibrary Name="RESUTILS.dll" />
      </Definitions>
    </Symbol>
    <Symbol Name="ResUtilSetBinaryValue">
      <Definitions>
        <DynamicLibrary Name="RESUTILS.dll" />
      </Definitions>
    </Symbol>
    <Symbol Name="ResUtilSetDwordValue">
      <Definitions>
        <DynamicLibrary Name="RESUTILS.dll" />
      </Definitions>
    </Symbol>
    <Symbol Name="ResUtilSetExpandSzValue">
      <Definitions>
        <DynamicLibrary Name="RESUTILS.dll" />
      </Definitions>
    </Symbol>
    <Symbol Name="ResUtilSetMultiSzValue">
      <Definitions>
        <DynamicLibrary Name="RESUTILS.dll" />
      </Definitions>
    </Symbol>
    <Symbol Name="ResUtilSetPrivatePropertyList">
      <Definitions>
        <DynamicLibrary Name="RESUTILS.dll" />
      </Definitions>
    </Symbol>
    <Symbol Name="ResUtilSetPropertyParameterBlock">
      <Definitions>
        <DynamicLibrary Name="RESUTILS.dll" />
      </Definitions>
    </Symbol>
    <Symbol Name="ResUtilSetPropertyParameterBlockEx">
      <Definitions>
        <DynamicLibrary Name="RESUTILS.dll" />
      </Definitions>
    </Symbol>
    <Symbol Name="ResUtilSetPropertyTable">
      <Definitions>
        <DynamicLibrary Name="RESUTILS.dll" />
      </Definitions>
    </Symbol>
    <Symbol Name="ResUtilSetPropertyTableEx">
      <Definitions>
        <DynamicLibrary Name="RESUTILS.dll" />
      </Definitions>
    </Symbol>
    <Symbol Name="ResUtilSetQwordValue">
      <Definitions>
        <DynamicLibrary Name="RESUTILS.dll" />
      </Definitions>
    </Symbol>
    <Symbol Name="ResUtilSetResourceServiceEnvironment">
      <Definitions>
        <DynamicLibrary Name="RESUTILS.dll" />
      </Definitions>
    </Symbol>
    <Symbol Name="ResUtilSetResourceServiceStartParameters">
      <Definitions>
        <DynamicLibrary Name="RESUTILS.dll" />
      </Definitions>
    </Symbol>
    <Symbol Name="ResUtilSetResourceServiceStartParametersEx">
      <Definitions>
        <DynamicLibrary Name="RESUTILS.dll" />
      </Definitions>
    </Symbol>
    <Symbol Name="ResUtilSetSzValue">
      <Definitions>
        <DynamicLibrary Name="RESUTILS.dll" />
      </Definitions>
    </Symbol>
    <Symbol Name="ResUtilSetUnknownProperties">
      <Definitions>
        <DynamicLibrary Name="RESUTILS.dll" />
      </Definitions>
    </Symbol>
    <Symbol Name="ResUtilSetValueEx">
      <Definitions>
        <DynamicLibrary Name="RESUTILS.dll" />
      </Definitions>
    </Symbol>
    <Symbol Name="ResUtilStartResourceService">
      <Definitions>
        <DynamicLibrary Name="RESUTILS.dll" />
      </Definitions>
    </Symbol>
    <Symbol Name="ResUtilStopResourceService">
      <Definitions>
        <DynamicLibrary Name="RESUTILS.dll" />
      </Definitions>
    </Symbol>
    <Symbol Name="ResUtilStopService">
      <Definitions>
        <DynamicLibrary Name="RESUTILS.dll" />
      </Definitions>
    </Symbol>
    <Symbol Name="ResUtilTerminateServiceProcessFromResDll">
      <Definitions>
        <DynamicLibrary Name="RESUTILS.dll" />
      </Definitions>
    </Symbol>
    <Symbol Name="ResUtilVerifyPrivatePropertyList">
      <Definitions>
        <DynamicLibrary Name="RESUTILS.dll" />
      </Definitions>
    </Symbol>
    <Symbol Name="ResUtilVerifyPropertyTable">
      <Definitions>
        <DynamicLibrary Name="RESUTILS.dll" />
      </Definitions>
    </Symbol>
    <Symbol Name="ResUtilVerifyResourceService">
      <Definitions>
        <DynamicLibrary Name="RESUTILS.dll" />
      </Definitions>
    </Symbol>
    <Symbol Name="ResUtilVerifyService">
      <Definitions>
        <DynamicLibrary Name="RESUTILS.dll" />
      </Definitions>
    </Symbol>
    <Symbol Name="ResUtilsDeleteKeyTree">
      <Definitions>
        <DynamicLibrary Name="RESUTILS.dll" />
      </Definitions>
    </Symbol>
  </ExportedSymbols>
</StaticLibrary>